mercupy/__init__.py
mercupy/data_elements.py
mercupy/filter_elements.py
mercupy/manifest_elements.py
mercupy/tags.py
mercupy-0.0.0.dist-info/METADATA
mercupy-0.0.0.dist-info/WHEEL
mercupy-0.0.0.dist-info/licenses/LICENSE
mercupy-0.0.0.dist-info/RECORD
