Metadata-Version: 2.1
Name: mercupy
Version: 0.0.0
Summary: Python interface definition for Mercury.
Project-URL: Homepage, https://trent-fellbootman.github.io/mercury.io/
Project-URL: GitHub, https://github.com/Trent-Fellbootman/mercury
Project-URL: Documentation, https://mercurynn.readthedocs.io/en/latest/
Author-email: Trent Fellbootman <trentfellbootman@gmail.com>
License-File: LICENSE
Classifier: Operating System :: OS Independent
Classifier: Programming Language :: Python :: 3
Requires-Python: <4.0,>=3.12
Requires-Dist: typeguard<5.0.0,>=4.1.5
